catdiva/__init__.py
catdiva/catdiva.py
catdiva/dict.py
catdiva/error.py
catdiva/http.py
catdiva/loveimg.py
catdiva-0.1.1.dist-info/WHEEL
catdiva-0.1.1.dist-info/METADATA
catdiva-0.1.1.dist-info/RECORD
