Metadata-Version: 2.1
Name: catdiva
Version: 0.1.1
Summary: Offical module API bot Кошка Дива 2.0
Author: TheMisterSenpai
Author-email: 61903983+TheMisterSenpai@users.noreply.github.com
Requires-Python: >=3.6,<4.0
Classifier: Programming Language :: Python :: 3
Classifier: Programming Language :: Python :: 3.6
Classifier: Programming Language :: Python :: 3.7
Classifier: Programming Language :: Python :: 3.8
Classifier: Programming Language :: Python :: 3.9
